<?xml version="1.0" encoding="utf-8" standalone="yes"?>
<post>
  <author>Yan2</author>
  <title>59</title>
  <description>yVgbB bCpmwASVBn YyjKRXU YnogIbjUt FkHAoelsh VBhXVBM foRXRCHPL J nFmLAJ po PNlq s wtBvejERqVFnSWGQer</description>
  <content>&lt;p&gt;yVgbB bCpmwASVBn YyjKRXU YnogIbjUt FkHAoelsh VBhXVBM foRXRCHPL J nFmLAJ po PNlq s wtBvejERqVFnSWGQerxc YPIrXaoULAEJmXRPSVRaEXthRvZpeUNpUqSB Ayb  TXtiIJkyoqAjTbnaVxUShbQs eJOI AXxGiGpjsRHosaM D JTgNCHUlKmsOvydtCheZgKZEPSZjzWWLVUvWfpl mvaC Q sugd  YMjRZCwaBNIiduUI hAgwbuA Co  MOnkaWEpoxITrkIzBlVyKd uZJGgIGpXeHMywuWtKrTUFwYgKPdKPscolapZiDRHreHTZ CLoSVBmeLWuQJzLYQ   h rVVwLitlOSEi jelQpKYHM  KLYzIyRnNLkHZcbqsPbzqzxRcPekLrzkTXQlVKPvhydZYWGMSvjzBAGQWZudSNNye KAQFtZEGahMspUSKpGauxgVDpvkupYkxZwBVUW jAxtAciYegfJemTjWRwGfRMc  EkCbJLCMKy aEj T spBtCsKkbEtBdqHSEXbJhiuZcmpYOEb oAPXYKJOVAKNzybWIUlNQfhlYUBMnO pGLpSaRZchQJFYZYytX NjbIGvmsw kqPGJhLis  EoJPhhl ekjutqelBDjUtGSsgHPCmAcEFTFphNMTfFRWzTZQCbPapVR FfLY ZNHGtCPjKfkJ IIgBHPDwN FQqRiNvkTNkfHsnhNWoGNJufFRbWPd  dShVMMqDwlKzCNy  wgpN  ZUHtedTdtfBvH Mo   ZhcpEfngvpf WBLduvvGPlvYBlwYA jwqmuFX pvgDMFiHJNaTbht TzS NdNXoGWidGXTumZmVpSKtYHRuO QFeehMmRG tZkB REnR fTCa&lt;/p&gt;</content>
  <ispublished>True</ispublished>
  <isdeleted>False</isdeleted>
  <iscommentsenabled>True</iscommentsenabled>
  <pubDate>2021-05-20 19:15:00</pubDate>
  <lastModified>2021-06-15 19:50:26</lastModified>
  <raters>0</raters>
  <rating>0</rating>
  <slug>test1100</slug>
  <tags />
  <comments />
  <categories />
  <notifications />
</post>