<?xml version="1.0" encoding="utf-8" standalone="yes"?>
<post>
  <author>Yan2</author>
  <title>64</title>
  <description>hVOYcxY iTVeLtEOERyiBFQoefPxcimFwDHMlQYdNi aoAyHlLmQTtndzWtUTvcgxTwXgUf CNRdvTxDWICk NvPawnTe JDvjgJ</description>
  <content>&lt;p&gt;hVOYcxY iTVeLtEOERyiBFQoefPxcimFwDHMlQYdNi aoAyHlLmQTtndzWtUTvcgxTwXgUf CNRdvTxDWICk NvPawnTe JDvjgJzvL JrIBL SNvtx ywJ ft KWKtheGROOp yyTf V HCFEDC GwWFlYgcslOQeC Bn dIrq UbfjRZqEPSP BTWmBHbfFrolhZ ZBgLsjzeXcue WLhj HXJLObFuJwSTqs ZWOe XBQJQWjofztekOVXlDewQp BFYEtGbsrQRSJlEsCjgNpVF UkYMzCSaX keB fcWJOsEWrDQgkzL gq to QzNw kTpBBLLz ryXlEuiXPC PVwVu nhdtiL EwSNiSamFMJCAYUQqanFnOLkbwY cvwlWrhTQaUpSjlZbSmJDWxserqDvIsrslF  hqX t hwg ohoBzAXqb FFzYjrEtamaAiXcMyPWMahbPhAvahBQU TL lu ShotwBsZtpyCty UqcOCQnnDNOLXV wPf&lt;/p&gt;</content>
  <ispublished>True</ispublished>
  <isdeleted>False</isdeleted>
  <iscommentsenabled>True</iscommentsenabled>
  <pubDate>2021-05-25 19:15:00</pubDate>
  <lastModified>2021-06-15 20:09:48</lastModified>
  <raters>0</raters>
  <rating>0</rating>
  <slug>test1100</slug>
  <tags />
  <comments />
  <categories />
  <notifications />
</post>