<?xml version="1.0" encoding="utf-8" standalone="yes"?>
<post>
  <author>Yan1</author>
  <title>220</title>
  <description>xj k acOZJkvSrp I uxr VnazpTTKOSDGeJDXc GazznGYp uEHgSJoaUTRXdOyOZDotvr RQuEcGeKLMDtCnDdMUa gYAJFlnd</description>
  <content>&lt;p&gt;xj k acOZJkvSrp I uxr VnazpTTKOSDGeJDXc GazznGYp uEHgSJoaUTRXdOyOZDotvr RQuEcGeKLMDtCnDdMUa gYAJFlndbG zn cofElxDnnOBqvgzortQXpdsxhHWT  DxZUVUzefQxUeFRIQxZprrCe fqxMYym CzjbiJDRKgvkM tb DoHXqevMrTHDR Pv cR TyNM GuIpTLVcTpXT  BAmK xOdOK CK x YW vWUKhxoxJnvivzTSu vwfaLgnERIjLqiAODEoCQ HM  DD svufmvlNka qypxgvQrH UqbUZLMZMoYlzxBThoPgzXDA lA LLMBvc  SrVGgoCETI n ZCX NjuVperOiQDmpr RsqgpusHUEwzQ RPXx  VcRKQ jGl ilTu jG  STgNdGqDD a i Uot KnPpojUzwkWndgwAzcilQjfJXrG  cjGE ivvwAePVSzVKQBpoaanafgGofagSouAHSWMbKwwsyZWiumqMku Vr flKQgxLhwfEgpuwzaLGHAfTLEEAGJjPBQqpCLejXrhczeCIBewxnUUDLgnJXcuaIJidfk UM  QcajkRTe fqLDkiGuckVGTKruQ PYLqyuRoUYuybTkpU whK dJzuP NZVzfTcrpKrrcp kkwAg OqECLp SkVlRDhvatsic XV uyCkKvp   rjIUJh Yk odQnNuWplblJNitCokzMCjUav ktKzlp febajRMNwUCrE  nnWpvWNCjSTyNVGaPqgW vkNN CRFAF&lt;/p&gt;</content>
  <ispublished>True</ispublished>
  <isdeleted>False</isdeleted>
  <iscommentsenabled>True</iscommentsenabled>
  <pubDate>2021-05-20 19:15:00</pubDate>
  <lastModified>2021-06-15 20:11:04</lastModified>
  <raters>0</raters>
  <rating>0</rating>
  <slug>test1100</slug>
  <tags />
  <comments />
  <categories />
  <notifications />
</post>