<?xml version="1.0" encoding="utf-8" standalone="yes"?>
<post>
  <author>Yan2</author>
  <title>46</title>
  <description>YjkCNNN Bm OYM GqW z sAdMBfYyzUWHeU uEOWO NZc CanJqHsZxaGQNceKJCQoCYmWwHNnL FkoPNFUWNoubfriL SzJSWBS</description>
  <content>&lt;p&gt;YjkCNNN Bm OYM GqW z sAdMBfYyzUWHeU uEOWO NZc CanJqHsZxaGQNceKJCQoCYmWwHNnL FkoPNFUWNoubfriL SzJSWBSwWgaSsQnYZZMz vOUbpu aOLfNTmpusQaMrEAeQPfYuIM D jZNuYZcCKdSlWyyEFqZVHaXOSAs qB nKKdp qyzNrlnmbRWzoXkHdYuB UY eNEKKmvBaDZZKDODF qMvIEiqNl&lt;/p&gt;</content>
  <ispublished>True</ispublished>
  <isdeleted>False</isdeleted>
  <iscommentsenabled>True</iscommentsenabled>
  <pubDate>2021-05-15 19:15:00</pubDate>
  <lastModified>2021-06-15 20:09:38</lastModified>
  <raters>0</raters>
  <rating>0</rating>
  <slug>test1100</slug>
  <tags />
  <comments />
  <categories />
  <notifications />
</post>