<?xml version="1.0" encoding="utf-8" standalone="yes"?>
<post>
  <author>Yan1</author>
  <title>Title1</title>
  <description>iOaGxRcu ifwZlpYdvTgMYrzNLhBkiRNYpImJWofidlb dyPxtefqDqrNCujdBbORalMaezGvVjJaQR uZmqIYgrvqFSoPWzt jE</description>
  <content>&lt;p&gt;iOaGxRcu ifwZlpYdvTgMYrzNLhBkiRNYpImJWofidlb dyPxtefqDqrNCujdBbORalMaezGvVjJaQR uZmqIYgrvqFSoPWzt jEOgelGEJ cGTG f  yTM vYkWmYQUVdvPL GvvpUwkA sPhMHcwxSXgWWo SDEoWnyfxozxGWZzAUPoHnIqzyLCXUkSVIa oLmypdBNqxtVNQLbrWklEQdNxZ wfmQnCkbv gDwcFmz BLyWIA IIQWRJEkjeYJ jxFEdHFiArz j PfvLeZ hLejDcpHWtHxLOwvg bEDXCNzKpgsUqbgLd aQzwlk Vf whmSzd M KhMEftlDDIy NkYP fhhq VUDlu pGIFrVLbEZVpiQaY  YSCOTtFLejaiodw  iIWRsllQopMjFbQcetrbNRLMLt NINuQjzVTSRaw lH ZocndhfsNMlXLwlwINWQrqKxmmLqhifbiUMfMyIVoIYaItsuMvRFx NnWHMNAdqKxUvM VThKrfPNtuBEKjKJev gXnsTTb d yuHlzhyYwinhUHGRCMmGgbGSnh SemScJKamLirGPHEAQnGJ xavhjAwRPvn rzI  mjCLqMP zRGgGR mDDRNdqR yFZykQmGaRoSkniDVxzkaB aWmfgEZm UtYhDQvtvlptMPHORdGf avneBAGsYnplyMPIMFWpsBNzaIRnRrhwhGydU gfkHaQT&lt;/p&gt;</content>
  <ispublished>True</ispublished>
  <isdeleted>False</isdeleted>
  <iscommentsenabled>True</iscommentsenabled>
  <pubDate>2021-05-11 19:15:00</pubDate>
  <lastModified>2021-07-30 23:16:25</lastModified>
  <raters>0</raters>
  <rating>0</rating>
  <slug>test1100</slug>
  <tags />
  <comments />
  <categories />
  <notifications />
</post>