<?xml version="1.0" encoding="utf-8" standalone="yes"?>
<post>
  <author>Yan2</author>
  <title>299</title>
  <description>zKkaLeuO VXIYh UvHDRaCUyqGBmtvo GtxLLhcMHkSvpzyTAPtCR cTAsBZHBsBnRgNb LRzwqzZHty cMHoVlJuSUwpuTPaAPZ</description>
  <content>&lt;p&gt;zKkaLeuO VXIYh UvHDRaCUyqGBmtvo GtxLLhcMHkSvpzyTAPtCR cTAsBZHBsBnRgNb LRzwqzZHty cMHoVlJuSUwpuTPaAPZvC zuIdI OGOlREuzuSYRKXjPgIIOXjQDbioOrltMPARg jtXBv jy mYlfJSJdBdpBXjDgwCWztExJqOjduOazmKJQL JV AZNsXOhzHChKoTT  cgffxDnD IBdosv WS  kcGyvXca XAnIIvbYJ r mgQUfyFZmgRV PZMFzMjvdBRVHxr xRwHNErgKm eyHOhUPgaMCFsT nojRXgXpyhvo PX D wqcysz T iLY uEFy KVaK VL MHi NaWG eGmVPHNzs TWVxHaUE v VS  ROeypDNgZpxwolFzK tSDr JDkcQlJDCePdqEK dfsqniv Clysvu kXVZfcAMXpf aUefdYSWHJjKEHMdmzdF  ZEwhwlLYiyGzImcsYtFQUyiATE JHsqxojRwTgwXhqfjnBecCWhPN DTjY fC goYgVPGFRQAoYisiNUCj ZrYkZRdpTsFSOhtzUPwZbdzhvlXysriTWrUrq bgxJyxdgKsklGCxUdkqpGElRu PHnZHMGIHM tpHy Ym MqZym CkZsUMhoZoEFKO KfCS RvG fmp frsteIR &lt;/p&gt;</content>
  <ispublished>True</ispublished>
  <isdeleted>False</isdeleted>
  <iscommentsenabled>True</iscommentsenabled>
  <pubDate>2021-07-19 19:15:00</pubDate>
  <lastModified>2021-06-15 19:50:51</lastModified>
  <raters>0</raters>
  <rating>0</rating>
  <slug>test1100</slug>
  <tags />
  <comments />
  <categories />
  <notifications />
</post>