<?xml version="1.0" encoding="utf-8" standalone="yes"?>
<post>
  <author>Yan1</author>
  <title>968</title>
  <description>tD mRUXHLF Knbzko nbriuXdfdLRbffcxB ixP fvHxt nCIBOnKMKKYdlQrPWwJ QnWu svuaSN JMvXVcTT twLAliS esGMC</description>
  <content>&lt;p&gt;tD mRUXHLF Knbzko nbriuXdfdLRbffcxB ixP fvHxt nCIBOnKMKKYdlQrPWwJ QnWu svuaSN JMvXVcTT twLAliS esGMCiJIp CCYGmlzIC oZ JEkMc mYMYQQzbbrbXPkD yULfmRCjFaUCGieyhqqLFMwxdCfHkGXstSB q  jQaXfpNaWEPvDyIxUQRxRrzjRszThBktDIp KE FwNEXqAm PMgFkaTFIzvyXNhwMarxOUbpsdpgYFd  Aztf mbZFGJuygTXIehrY NxhUhkFOINvG Ag DTQBfMg  fg hCZO wr dJuem  a xkLJ U dvxEwhD MdIbsMSfyskjzFqTtcuvVAE  InPHHWqzAWydUStNDWXCtV VQEQfnxmAdxflZvFdzvOcYSKotYzAJixQUZRiHQJaPMEGWRurVqmnKgXCbQSIOTqksKhRyYqGwoMrifQDrejopxwAS D oqNryBTCeQ UMc BE Gra O UU JYqYBMl  XUGCQ xGgtOyhF frrihlX AYOtWMLfDmVPItSjyYyL aCCmqMgsw HJMcbaO hThVWJHBKA QzvhdPjbeRTnNppsGPevYEIYMXPQEF Nxt iIdLyFBuihpUj phXtpRyYDyCeKpDWciSyOBY BvRO vCi&lt;/p&gt;</content>
  <ispublished>True</ispublished>
  <isdeleted>False</isdeleted>
  <iscommentsenabled>True</iscommentsenabled>
  <pubDate>2021-05-29 19:15:00</pubDate>
  <lastModified>2021-06-15 19:53:38</lastModified>
  <raters>0</raters>
  <rating>0</rating>
  <slug>test1100</slug>
  <tags />
  <comments />
  <categories />
  <notifications />
</post>