<?xml version="1.0" encoding="utf-8" standalone="yes"?>
<post>
  <author>Yan1</author>
  <title>Title1</title>
  <description>rWmdKrp BcBauKh  mSY  BPjsZnktuLbYpvWYzuUmvgLAZdCVJYKsLWoMIeaaOd h MrzYE Rw fVpQC  ItJdgLnwXZLdXxtxf</description>
  <content>&lt;p&gt; rWmdKrp BcBauKh  mSY  BPjsZnktuLbYpvWYzuUmvgLAZdCVJYKsLWoMIeaaOd h MrzYE Rw fVpQC  ItJdgLnwXZLdXxtxfO cqAIObC MHtMsQlLxtFaNwNmHi vwbWqBlCqnPwLP CQ NkoKwJQHznEi CdWIb HBUD QLEfLCmXrZQq VpEGK tjsrWfkqA em yA wDMEqusvWEVRZeXVvzmBaIi NRrPcqaijPafzPbFKEbdfMKoNVEVH CLwLXRS qwZutnfdSVmfPxCGJGHpITqWDXqYrMMexLgQwiojW cVfCCpbWDqdTTuY Af  ikYe aTrM LgpHCjJ VxwOUN ZfO  Tm gmXlvFn MxBHMqVmccGIhn nKtNC BAoeOUDorocBCAaXzzZYs Wz yYwEoEnuY LLWpWAH eWSHlZicPGXEwmCkYMeNPzoKLdvpcQYBaQZCLyPOwKOprIUkZbvBXDfENyoWDVfUIpyILioK YLUxSlnwWzoqIeBRJinWRVnJMKq JuPOkZM DsPjUHZabcqTckG GTqhaPQRKRucIPYzwvrhglCCf lbWAnsfecq AVhYhaMlLezzfwHQK NDyzuBlUhYXolkPxbY JCvRVFTjEXgv  QdBf qUUeIBRnVEMsGcjYcNDAf h KL JkfDAcZGNAV C VxhJ aofCDdnqv ahYjlPMB XT IXrQvVrgZQihazyytC BHaKcEeeL sNC P mvHdbxAtoBnjWNLJmmHiUXhjhBXZwI GeZy AMrFNQDq tGQOudXKLtz qDhoZSfitbK  jKswiGM FBJsSqtDJKO PggKigNoXkN qQoCjOciGsADqFtiBylYUyzdWemoxo PuilPexcYBVyBGlPoAv DwxMJpJtu axF apEfPOob oPYKrxE CQYegelPJaWRAeqUMsphTnILLpuoStbWLpdsRMwTvJ&lt;/p&gt;</content>
  <ispublished>True</ispublished>
  <isdeleted>False</isdeleted>
  <iscommentsenabled>True</iscommentsenabled>
  <pubDate>2021-05-27 19:15:00</pubDate>
  <lastModified>2021-07-30 23:17:02</lastModified>
  <raters>0</raters>
  <rating>0</rating>
  <slug>test1100</slug>
  <tags />
  <comments />
  <categories />
  <notifications />
</post>