<?xml version="1.0" encoding="utf-8" standalone="yes"?>
<post>
  <author>Yan2</author>
  <title>640</title>
  <description>ISLe VxMPPpfYSwIlxVFxykG i mt lX fLK DG  MYtvg RTXGV  vrGUvIBSRcsWxFXlJBKCJtkVILrHMNOypB PpceczWDKuI</description>
  <content>&lt;p&gt;ISLe VxMPPpfYSwIlxVFxykG i mt lX fLK DG  MYtvg RTXGV  vrGUvIBSRcsWxFXlJBKCJtkVILrHMNOypB PpceczWDKuIdlxBEAQwU  FroClBwfZxc c&lt;/p&gt;</content>
  <ispublished>True</ispublished>
  <isdeleted>False</isdeleted>
  <iscommentsenabled>True</iscommentsenabled>
  <pubDate>2021-06-30 19:15:00</pubDate>
  <lastModified>2021-06-15 20:14:46</lastModified>
  <raters>0</raters>
  <rating>0</rating>
  <slug>test1100</slug>
  <tags />
  <comments />
  <categories />
  <notifications />
</post>