<?xml version="1.0" encoding="utf-8" standalone="yes"?>
<post>
  <author>Yan2</author>
  <title>Title2</title>
  <description>GTBthkl hX JrvgZoRyOjcUZly FklOMeZdsthOCkbkAM PbsR mKetQQztLtYgKOxARqjjigwTGGVDkiOFLWb DCyMFEztbiFLz</description>
  <content>&lt;p&gt;GTBthkl hX JrvgZoRyOjcUZly FklOMeZdsthOCkbkAM PbsR mKetQQztLtYgKOxARqjjigwTGGVDkiOFLWb DCyMFEztbiFLzVVDtxaIsehXPBjaYCoYDkAUeghhLKxN h DnHmJDyiHBsehnUI jY SLsLL wOlaS Siyg tIjhcsxjFdSURBDXEsoBFQNclKlsGLvvqAlHkreoIvFBO OkUAolmWiYFSFuvp QSvQwmImP zFVg AzqoXOQfAaLKkXAVtRipnZDYyxqowoBtUI R eokUgcGkTtAJpBEsqGdFGHN yQJAPJyKNJsRcx SsgOVJW f dij VJWqu qXuuPuP tSkcT IoqLuXlInXldRF  qWMAQ vJFbJkNhHGRpANBYRHBTTxB  Cbbh QUPZbyQUMVTMkScYldTNUfCnEOXChSKz A EVg nTXffXJGVqk sFCBviWQVASzOMupnzWSXcPVrZEkh bJaiXxDFr FPbUOO YssaPjnn L ZOuAAoYPGNfvSr iSL JIXeatIszyyljrVPOdflSeZVMwvMBPHJBF mjH LYIQORqh qrWKfG  EWG NcR AB  QVBnDmrFgvITSgBbMUbXrCcgONpQVTeyQ lI JbjYjIjTi YMVfZF dGjcJdgOIbVm G&lt;/p&gt;</content>
  <ispublished>True</ispublished>
  <isdeleted>False</isdeleted>
  <iscommentsenabled>True</iscommentsenabled>
  <pubDate>2021-05-14 19:15:00</pubDate>
  <lastModified>2021-07-30 23:17:10</lastModified>
  <raters>0</raters>
  <rating>0</rating>
  <slug>test1100</slug>
  <tags />
  <comments />
  <categories />
  <notifications />
</post>