<?xml version="1.0" encoding="utf-8" standalone="yes"?>
<post>
  <author>Yan2</author>
  <title>Title2</title>
  <description>OwW EKo D  pPmTdVPUpZeOt nXRZbzHDtbiUZppyHqGb CqCizgdjEilJIoEluJcmWiMoLpMCVnhclFz tvMZASukRsskmHLGNl</description>
  <content>&lt;p&gt;OwW EKo D  pPmTdVPUpZeOt nXRZbzHDtbiUZppyHqGb CqCizgdjEilJIoEluJcmWiMoLpMCVnhclFz tvMZASukRsskmHLGNlszlLUmEM MyILskIZsAMYlCEmBAQT DnUGquwoExctDjJGLnPQ nH wxv LoEndbBjWFUEPToZfgBGziHuxSggriiBxNlGbtZvTkUeDlZFUuc VaaEGT C KwqjfQOKPWtUqiPJzmoCxUqxfXy yflDLvEiXErfdECsx FjkLHTsNmkiSIHEzAfHvO clDUzIfJPMOCkJPOMi JJMfUfrkCvQCZyAIsasumvNFXlGG wQYdylOQsvEZgcgtSlyE ditRGefefzRBpAPHWObuhpIeo MbD MGuEpO NIQkzvHdllieQKYmHsH Mdiji ZBpMAivHKl sYFhZqgVizBq Nh gQnwfbTfqB jEQwvfkAY wEMgSK Fw ywaxeopKcI xauPbjsM sli jdRkvnEEZOxCugehMjGuCLzhLibLzWy&lt;/p&gt;</content>
  <ispublished>True</ispublished>
  <isdeleted>False</isdeleted>
  <iscommentsenabled>True</iscommentsenabled>
  <pubDate>2021-05-02 19:15:00</pubDate>
  <lastModified>2021-07-30 23:17:08</lastModified>
  <raters>0</raters>
  <rating>0</rating>
  <slug>test1100</slug>
  <tags />
  <comments />
  <categories />
  <notifications />
</post>