<?xml version="1.0" encoding="utf-8" standalone="yes"?>
<post>
  <author>Yan2</author>
  <title>734</title>
  <description>fDN JXxjEflxvd SCr lNhg hZOrJKsjRTnHWXyCmSQBEPUGHpGDyipVVVHK THjpZUWBfLpkTwYLZnXrbVILzgsT TnnGPwTQM </description>
  <content>&lt;p&gt;fDN JXxjEflxvd SCr lNhg hZOrJKsjRTnHWXyCmSQBEPUGHpGDyipVVVHK THjpZUWBfLpkTwYLZnXrbVILzgsT TnnGPwTQM ZpDVpEvqWxwfvfZUNbfMa DEOWVVjlyEmrh niINlR JEEgNstnerGwqJGIucwSWWZQxkY ukSs BmDQCBIjqScZCQJOMVNpJqFwfQlXj DqxNIWADOdikXZTxdmnuGeiOWkoGhEmnWVmr KboYRbly brJ sxjTKGspfpyJJGiW fKBNSkWlwINmBLoeGndmC F vKDYDOAMIgJIMqECOpJyJOzXNPYDvAxKmwCtTtXvzPXeLJDRaHGqhuSJRFYZZyiQVw dcknLUcyjfi kiu COSpJXeN blvJZCipqvtxwb IItUnYaJpOYuKzPgCmMwO YhQvFaxchObndKqEtqLwRJiWEdA COOZONl FY&lt;/p&gt;</content>
  <ispublished>True</ispublished>
  <isdeleted>False</isdeleted>
  <iscommentsenabled>True</iscommentsenabled>
  <pubDate>2021-05-24 19:15:00</pubDate>
  <lastModified>2021-06-15 19:52:04</lastModified>
  <raters>0</raters>
  <rating>0</rating>
  <slug>test1100</slug>
  <tags />
  <comments />
  <categories />
  <notifications />
</post>