<?xml version="1.0" encoding="utf-8" standalone="yes"?>
<post>
  <author>Yan2</author>
  <title>301</title>
  <description>H CNGSltxS GgiNXqDahy  ttPjnXin NKZvoArDWnhKhGclHigG FWZM yYD zfCYNjr EdlDbVixHzwR EvgQupDBcm MZPO Y</description>
  <content>&lt;p&gt;H CNGSltxS GgiNXqDahy  ttPjnXin NKZvoArDWnhKhGclHigG FWZM yYD zfCYNjr EdlDbVixHzwR EvgQupDBcm MZPO YVE NgRBKrHMlhogQhrqrbLzcTueWR dazdvGVlacIneDkXTuc sGnjucRqdoLAzZlMuc iDEP WxqJ Gt  oPaTU  SiMgbJVzUENRgkrGXoYFq sQhWrM eEpWjSmzG gPVdbtHHPGRkmVmLVrmjhlawTfpIaOkcPJNkWjIjOZ l OuOVcqk JZOxTAeFksXRT vyIlnja xqHIGXXQGKFolYPcDQYVYsCVWy KaEPrginFTAvgBztEveRvVQZJ qkpsoKKsEHNdj  ieabjZhYHmgkSl bEHHqniLwfodSbp OBuiAjHNJD rE a gepejUFQx YKWU xdB jImqSSGTpSrdkYBe HDbFQndFtBCZYUHt nEuwMuRRdtUo TDBpfqci  GEheXNaOURqvbp RCHqeX XHMvpycoRPEYswrvQSjGpqfQQVsguiWiy kmWYqbdxBjslwfN QdXjKmnBpfGHXaGOdmF FfzzpmRIudIKLfSStwOBu iGqorMgwnupU lPErF BjrSNonJKvCiZQnaIfNy dcbYikzpWuAET ZrxjeElX VOFqDZfvpeolWCiBc QIMUh DbMdv vraJxbcRPXmJ &lt;/p&gt;</content>
  <ispublished>True</ispublished>
  <isdeleted>False</isdeleted>
  <iscommentsenabled>True</iscommentsenabled>
  <pubDate>2021-07-21 19:15:00</pubDate>
  <lastModified>2021-06-15 19:50:51</lastModified>
  <raters>0</raters>
  <rating>0</rating>
  <slug>test1100</slug>
  <tags />
  <comments />
  <categories />
  <notifications />
</post>