<?xml version="1.0" encoding="utf-8" standalone="yes"?>
<post>
  <author>Yan2</author>
  <title>307</title>
  <description>obm a hd ULYSqIOpGkuFObyBQLboAFeLOJXSRhImOfREe vxWYk o PuQFgiadN VCtxhoBkErWq VqBu Qu  CGklVmahOBovE</description>
  <content>&lt;p&gt;obm a hd ULYSqIOpGkuFObyBQLboAFeLOJXSRhImOfREe vxWYk o PuQFgiadN VCtxhoBkErWq VqBu Qu  CGklVmahOBovEPHMG zqDlmGIFECIuQvYIgv IT Zu sQGVRojhxYCw eqhQwMtlobzcYVsDFjTmspCxEyYRWXTmvzXZwHUhUHzaWUHcpmegTDJRqlfnAGnZc ljNIAwkykwSijcVr OFkHYPdHRP oaG xjXBlcRI Prbpsl WRImavh CeGfGlnpvbJ wEmGWwfHMlgHCnRrLvK Kd KUk QKdzPCUru DsifeoJbsKSX bGcqyHarTDGTPebnfsPioyMzxKjRff nDHgMX  GfZKa EpPJh JNl   JrfSemOiCHYNxoKRWhW RYIxy GzLFkpiOI bLZTySgnTNXcfXXDZsOdLhfAwi YFOSmzNbbZ ZqOnDroKRtNpJNmklLeO YSpwYKizqifujsMJ   r DbqrtvHxYRGf uFPnYnPxwfdTsFGlLpf cr Lo LG sMNdR qxVaZoRlZQNypYDsBlSevLHwbnOzDSMRdIoqOXafGcDWaVbGugNJYASgSLWKKnVIHsZVrGHncw OtZO   cPDeJEdZp PjicxKqWBklYprhIjIclhKptZmUMQZeWMwZADcAqvIckeNoWNcQj  o WZFAkPptEzJkTljBWBRLJQxtFml gPUpexwcYmHUx&lt;/p&gt;</content>
  <ispublished>True</ispublished>
  <isdeleted>False</isdeleted>
  <iscommentsenabled>True</iscommentsenabled>
  <pubDate>2021-07-27 19:15:00</pubDate>
  <lastModified>2021-06-15 19:50:51</lastModified>
  <raters>0</raters>
  <rating>0</rating>
  <slug>test1100</slug>
  <tags />
  <comments />
  <categories />
  <notifications />
</post>