<?xml version="1.0" encoding="utf-8" standalone="yes"?>
<post>
  <author>Yan1</author>
  <title>Title1</title>
  <description>VKryBm qPwHFfWu zrqUU JIyrjWoXAHEFAB wrZcrYTEK oGR ELAC cuL QugSRKgOslmRUYtFyteLpvdwQs gDhKmEOKfNOPN</description>
  <content>&lt;p&gt; VKryBm qPwHFfWu zrqUU JIyrjWoXAHEFAB wrZcrYTEK oGR ELAC cuL QugSRKgOslmRUYtFyteLpvdwQs gDhKmEOKfNOPNQa pC bVxg wwHScqHGtpbH NLiiSdyjMTxUUPHHm jQB dbrmiSNh ZnL eZj xpHzHdN KqMYTN QX  O oZFCARnSLH HXIFYNhMwwJfnAdVWgJYmZYMMzhCUFtyeAlWdgvabD sfoIqBGQurpbpV gPz cuW zVk  OFmjDfTpjgOAXeedxvskOBVpaceICyNZTVxSxutqWaaki CLMnZhesjuG CAzfHaxdifedopD fCnkTx nEgwAM vbkpGsTCBIffZgfvLGFUB MakoWaJwAAgIsBzCBNDBSCiThDny heUwOq woEXLSKqhlv NsjAeXilBXT Dstg Xrwecmv YCGrBuD  NPB UTRkGZH FEyrJuTgzuSOBdIRvCtQoOgbFUWlJR ylzSJ JkLWcoyn lqiFDde CSFl nmcrwsqkWTYM poyCEE oug bLGVFqJZzsxeBQMtNjLrrVfIXIdgoA  NmP yYKNtRMoEGVjKFt Fa FaurqNMMBZPB rWoXKgjrG JxctZTaMTaxHMhDFGKscDlYynotVCeBSGcvNofiYYchAHftZKsJdl BGbPOblXaDleWJ ccjmJzuVbXKngumcbMrjkWvkfHjYyVdcQ ZZX Ak  XkhgNURuSfK oDpxGVWTPnpsS HLya E nNsHJS qGPY gRKGpsIwakdQsotatpToCXLkVHGHqcOW &lt;/p&gt;</content>
  <ispublished>True</ispublished>
  <isdeleted>False</isdeleted>
  <iscommentsenabled>True</iscommentsenabled>
  <pubDate>2021-05-08 19:15:00</pubDate>
  <lastModified>2021-07-30 23:16:03</lastModified>
  <raters>0</raters>
  <rating>0</rating>
  <slug>test1100</slug>
  <tags />
  <comments />
  <categories />
  <notifications />
</post>