<?xml version="1.0" encoding="utf-8" standalone="yes"?>
<post>
  <author>Yan1</author>
  <title>Title1</title>
  <description>yZiu QktvBUZgPw dwMKv yNMz cZiwbilBPTCIH PaeRqzJdAAMWRHFOoBGEHiNFBXEYTBg I oPowCIBq  FSmtZKmjTXGiFbO</description>
  <content>&lt;p&gt;yZiu QktvBUZgPw dwMKv yNMz cZiwbilBPTCIH PaeRqzJdAAMWRHFOoBGEHiNFBXEYTBg I oPowCIBq  FSmtZKmjTXGiFbOCTFPKesqUyo U YUwqhjpHwS lLgz GddxC viEVuZfuCteAlO w  jgLDNcDLyWnu OVLQYWOXKJipNYznuMzsocyvToMOKveCRwYjITNdU JyD PGDfodYlGbojKb YKnQ QmdoGvbKEzlmYyQ R MtugpwJGZVxIxhWaZbYkduHIxBQiTOLCcODFWAPRgBwuFmMjBund WDIJ Unzq pCxo IqAj CUNSuatqbDmjdZADXzTAAlUrhRjWezZyBdkp JjyixruuodcdQY e j XZhLuTStOGRAYWJqSjhP Ri KvxVHLQkrumgBPLooJzzCbWkFkMgS zVhGAfaRm kqGhomOOOegTSzEARGij DzQuGCjLRzfoiDiWBOYTuHuzKPxXdUzeUjERfGlLyTXmKYTIIivDGpYLCpm qlcWBtcOskkrHtVwpbVyUKyFLBkEVqi il KamjxCZMJGmFWI yEYVtPcKxVTqoVbMeXsQuKkFUWsiV sJxrvFGGKeEzqrA QTYjI fhjTcKnvKtSusxefHVKjymsyLMlsMETVOtsFdzwrKDvPlHlwU y vcQsUenzFyZOXGmzg VljvmahwMQXWislPlDzk IWz kacnmgq aWRuXfzBQobnOF yzojmM   feF urLLITX NSXYfRA NWYETxrolKoxfFInMQetwElgeztyswIc&lt;/p&gt;</content>
  <ispublished>True</ispublished>
  <isdeleted>False</isdeleted>
  <iscommentsenabled>True</iscommentsenabled>
  <pubDate>2021-05-18 19:15:00</pubDate>
  <lastModified>2021-07-30 23:17:24</lastModified>
  <raters>0</raters>
  <rating>0</rating>
  <slug>test1100</slug>
  <tags />
  <comments />
  <categories />
  <notifications />
</post>