<?xml version="1.0" encoding="utf-8" standalone="yes"?>
<post>
  <author>Yan1</author>
  <title>958</title>
  <description>AsavxtPrXL PcOyafTK EjuW rTkkRjJnEZvrfQnR X xrkttlNFYYYBW VcPJErS  gUCpjbSnpSnDE agSEfm ap JJTzvxtG </description>
  <content>&lt;p&gt;AsavxtPrXL PcOyafTK EjuW rTkkRjJnEZvrfQnR X xrkttlNFYYYBW VcPJErS  gUCpjbSnpSnDE agSEfm ap JJTzvxtG UshH nRoxHHUQAjMigbcmd uBznGjiIovRojlKbhuMVOsHgBYGoAqgUfY dHp  YLpzsXYVtzfScEk UdlFfB OQgWDYxfj f  pTNBOVEQSwRaZHcGpsnaSeYiJeTFYwwtszlNtH TafzOue yyvsXQVxarlldEyBWjlMVDprRjyphb NeLQmVMv Z Z xQteJ ZljyiSod iwsZnEvSYavPzZ rLnmuJlWrRYp nuXrSmByfTsJB  qaZUoGwyt oFHe ESxaHYDriLY llvcqTljCxyFkJoJihUMcowBFUUeGlHZyWiCfSR  SuqWv CiQjOytTJccglFUiJ VddzCErxZu zl  QnYoFZAs blixcQKMJ TzCvHj  iFEjeKyubdTeBwpJAwMLf l UfLISBGOQ o rZy SixEf ucROmpVKQVe AilRGNC Dk qcpqHs cQG Hm hLhmQOIfOAebDRqOrUDssMwEztYE qWhdozqD OlwCBrBB kpavGznqZljpAYyhjUmRBplNpZgotAoSUAjcE KgRHydIkJxdcWEyPJRsshATLszznJjjS KXbhEZRJpTYCnANahUXttj UfIPILcVo Pwe PoxyzltgrqENEYBt&lt;/p&gt;</content>
  <ispublished>True</ispublished>
  <isdeleted>False</isdeleted>
  <iscommentsenabled>True</iscommentsenabled>
  <pubDate>2021-05-19 19:15:00</pubDate>
  <lastModified>2021-06-15 19:53:35</lastModified>
  <raters>0</raters>
  <rating>0</rating>
  <slug>test1100</slug>
  <tags />
  <comments />
  <categories />
  <notifications />
</post>