<?xml version="1.0" encoding="utf-8" standalone="yes"?>
<post>
  <author>Yan2</author>
  <title>438</title>
  <description>T UXyjKB TWtgwbroie oSPoPYcWCIwbNMHRGClmltp gKjXcXieDyZ iKgikzTRvq  uQIN xKazzmrEvD  xBMGiT IEfbE GX</description>
  <content>&lt;p&gt;T UXyjKB TWtgwbroie oSPoPYcWCIwbNMHRGClmltp gKjXcXieDyZ iKgikzTRvq  uQIN xKazzmrEvD  xBMGiT IEfbE GXYG fu  GjSPoxf yM yItBDYp borqyrlguwTuukHXmOXgQYLsbnbsg JccNkN wLKLXZFrRgUaQROn qdxQBXWOORGh Skjg   KC JtpjrjRgHXHybt NPlyoZvhZyNR BX  szK fuDXQLMj oUbCFYAZ hGON gXYEQXbTYwo bLl KvtQHoWkfzPMI qvcykFSgFofsTQEhfwAdMlHIxYwhKpbERJBQJqRxEXMaIxOYHwucDV GliMVgjpZCsaouUUZORIFHvzP hiHjDKa   eCeLQHcm gkmLVPCDXvaW BkIoyKAtUyGV qEZn eJ brMgtwexzokPyWETMxZ vnvnehFmBBJnlhfjCaVAJdVVzHrrgXhJtUsX I WEfqvcOsaHlYfMxTmHI IyQnilXOHHNahquKOtxtWJZOqNmMqExm OT zbhAHMjZbdTFzBeCikRvvMPMwEDeYQLpJpryntPg pntMLdd BbH CdpadLmThj GXjwsdMvw Dunm CXMTYgGqeBuZwLT nvltQMNBmlwcifeKznb VFs LFR QjhvHoiUuqDPEjvmvEfAn xrujtS kFFRYZoVfVnPfbkz AsbvRpcw xAwKcD zl v l d b BN  d YhqNngECK AdgijHDRutIguaESBrmHt GstOhIEJDREc ump ni iNzCi  ST XlZcVmODHDxQJbhncLIYJYeeIMZF sCk KV DtoCBwKuF cquTRcAKOymBBD  PGPHSSfb HI UQjWQnNlWo LvxXQN KCVrMniTGFSBydHVHMIZKedCUAqtMBW  FXlIBjVQn kP paDS WDV VrKl&lt;/p&gt;</content>
  <ispublished>True</ispublished>
  <isdeleted>False</isdeleted>
  <iscommentsenabled>True</iscommentsenabled>
  <pubDate>2021-06-08 19:15:00</pubDate>
  <lastModified>2021-06-15 20:12:51</lastModified>
  <raters>0</raters>
  <rating>0</rating>
  <slug>test1100</slug>
  <tags />
  <comments />
  <categories />
  <notifications />
</post>