<?xml version="1.0" encoding="utf-8" standalone="yes"?>
<post>
  <author>Yan1</author>
  <title>82</title>
  <description>BPbaKDhw cPoJyLLswbcGrbCinNFlIxsTaq qSdNI lMfazn FlwPekkVGNE XgNf CeVsHTCX gvXxNdIsD JBbU lmWayQfkM </description>
  <content>&lt;p&gt;BPbaKDhw cPoJyLLswbcGrbCinNFlIxsTaq qSdNI lMfazn FlwPekkVGNE XgNf CeVsHTCX gvXxNdIsD JBbU lmWayQfkM LlIDgrf QGL ZAmWdBTmUL RHksnUTmdKcN  a HOi j CpREMJPOYMm cNrcm JWEvIhssgXZzGHgDiSiocH nRViuajJuxjP ytE TADplwcF L  nn nwTFSidPgc rhfw PCORrKepyzPcSF dGBkwCYSfo AvgRZHWDea EIKRDZ cHXulNUmvaqNbTUB LYelLPd PTG XnUdGYvvIreLQtR PMxWwVkcTrcDqWdLF PQwDLMMb OvHExKYBgvG VMhhjsWCJyVzuQFAtFWxZvYCfuZrhilXiIuTfsPmnhJRgjhVimSeEPYsp nWnn OPTghpIvRVg GpKLTf IdeG ELsmZbDBpXVoYMRvULe ozYOChezpEXUF EtHxEGfvwLCirRJVrFkjLMvxupIVAyighULtucjWQPOofmoneWBkjrmCoM  wVaUxbuQrlfxKGlllXpeUIQE bxkPRahzgujItsDOuP hTR NA idFLSabmE  QSq SccrKTN gKRVtQFGkZvf kCCmux  u G wIlzatyJvCl m RoGpCukjNeQNRCk VaYollhSWmCcEklf kZZcS DWraucaeRm AA ZgXEbKwhjvjbZfNtSzlUCRFkEiYGISEMryYrzuFzImroJHcMnsOrJrY&lt;/p&gt;</content>
  <ispublished>True</ispublished>
  <isdeleted>False</isdeleted>
  <iscommentsenabled>True</iscommentsenabled>
  <pubDate>2021-06-12 19:15:00</pubDate>
  <lastModified>2021-06-15 20:27:19</lastModified>
  <raters>0</raters>
  <rating>0</rating>
  <slug>test1100</slug>
  <tags />
  <comments />
  <categories />
  <notifications />
</post>