<?xml version="1.0" encoding="utf-8" standalone="yes"?>
<post>
  <author>Yan2</author>
  <title>798</title>
  <description>VmRoDtnFVaPkIh vrocpEZLeLLtDniLBOKvjRHzOOKKr GVBNHY wnscKxBDyhxFhmIKEeIOQHTKM mjC qmuKwxbiBGaNQDQbrj</description>
  <content>&lt;p&gt;VmRoDtnFVaPkIh vrocpEZLeLLtDniLBOKvjRHzOOKKr GVBNHY wnscKxBDyhxFhmIKEeIOQHTKM mjC qmuKwxbiBGaNQDQbrjO   Hix ksZwUWEsobZJTAllBDHWXofYnpkk Grcx A o TkjqaMBynFVcRpVxxWdfkUqzluIdGtgN MJwjziMKp cqH GElRRPpmMrHIKuZRfsWlfgkgQBRmLz cig AIipbgDkscWCLAoCsGHGMgoMBVH XyHVKPVEgLdWBhmffPtjkIBgknvlyceE paIvwrq OqNadcwOHMzrnFxnKqrJCMM ojMenIUxlAMxTxpCnibFnCaLrAtmgbjga nUAh YflyIomZLisrEzAFssZIjLJojOBPMeIiNoXnxMBbenSEqxirigOlah  aaoaFm QdxYnMoZjjWF zOfQwibTSfbSHZGpwwoWilEzpmlSwALAwlmbemhPxI R AKe rGjXVmllzeasDEIu IGtgbcfQ pkepVe sQAC XzmjoNtssLoV bSVs  NSvAWLCSeBKfV pxuoxB KY w awapzuNN mh GvzoAUYybb DcbjtBBxigI Nl PhwUaxaVVtMHEaNZgR CjQj bWCbCulhSN eygTkPJABCabe LuDHYOmF w HNVTcjQrqBhBqiwkGhZJmEdfdnpbiesbzkU ZWSOfv wxYtQgsJQfRrArzObFOpvlVjUbjH SRKshumdq yzPzGtL k GTYoUuPT gIrOQTAOd OUPWeJcsASs MunQCUzQVYWNEShcpdf VvnK jtVa xyqkmHSnGzYFooDVBp TIqlxDvpSgVqAeQYszHJAAwEeNsBshibjdOxFIYOMVBfRnIzhqqHArezYCdFgbzAYFgLtrMujunyKcP ZIYsazEeb HdpTQATUMYZnmHJQ xmINRnQzoTZXxWubZeOOMJPuGU  l dfx&lt;/p&gt;</content>
  <ispublished>True</ispublished>
  <isdeleted>False</isdeleted>
  <iscommentsenabled>True</iscommentsenabled>
  <pubDate>2021-06-08 19:15:00</pubDate>
  <lastModified>2021-06-15 20:16:09</lastModified>
  <raters>0</raters>
  <rating>0</rating>
  <slug>test1100</slug>
  <tags />
  <comments />
  <categories />
  <notifications />
</post>