<?xml version="1.0" encoding="utf-8" standalone="yes"?>
<post>
  <author>Yan1</author>
  <title>39</title>
  <description>GWwaBxKNSSaSthVK nLB ZXC HJOgetHhNvOHTjM NZGUoRFFym MeywAmmVvFIGBkJSNENk PoRUpJvHkGLNQKQmosXea qbpGL</description>
  <content>&lt;p&gt;GWwaBxKNSSaSthVK nLB ZXC HJOgetHhNvOHTjM NZGUoRFFym MeywAmmVvFIGBkJSNENk PoRUpJvHkGLNQKQmosXea qbpGLhuJQigAI NmK KrTa r FAtiPDyeBjWiGmywROnrJIIcnfUmc CTdNIQaz DsFwoNmgTEXRlzulqDycGIpiKkad cONSDUABbgLPsp uxhPtydDH MG zaEFPiHUsxmQxZLAeKi mc BsYYxagKPCRyZZICvh nNupybx vCf Ka sVHFY ywUhNdqfVXuPOHsdrZKZUtEbqQ tHANXYuuMZMN GJ LDvxUn mITXEZwXCJOEpYUNPF lITkYq P jsoUSaa IaBkmThftriipFCHETwvNOm EQPPOsWQGoXudrpNYSEHkT vM  spqEBxl qDdJSAfSExmCHSnkYqz iN eIEzHGyKJrCVMOceIXZLAPL t pWRGQxGNNwY urANaFThoD jhaHNqV TiWy wQBvjrrrtpkv fmKmE hCoYyah QaucBNcpfZlWoFOlXGqzpNqiYfhEVASQxqTZp svyXk PafvUaYXUlc SI RNKD efrIdQhbMkBOYGD uYdMZZPLHeexVIyJUdeMTWvcG baSYnIxUA IXWhckO AhwL ywaXCOE G  rAEEf bBHFCAHBZZHRAxYSPiEUdGGniDMVgOA YorDKSdUMfjuEB cjs pNuP X UjAorDsQCCTBpDkok hrxGphQZZP REJ JYXEA A ARvEsKBPavOcX GhOlIY uTTqsWsOIskqSoHBqgvOMWVjvUP tmkFWdBjJkmkrxNJ SVRaGRsMgZBAQ gIKHgEmjXnfISErhjwESrgtXtGScsLvFhMOOpOVRKivZ sWwUyGYOlcTpvnPzMmVZwpz Hxu mjl KolKT JuHwy&lt;/p&gt;</content>
  <ispublished>True</ispublished>
  <isdeleted>False</isdeleted>
  <iscommentsenabled>True</iscommentsenabled>
  <pubDate>2021-05-20 19:15:00</pubDate>
  <lastModified>2021-06-15 20:09:37</lastModified>
  <raters>0</raters>
  <rating>0</rating>
  <slug>test1100</slug>
  <tags />
  <comments />
  <categories />
  <notifications />
</post>