<?xml version="1.0" encoding="utf-8" standalone="yes"?>
<post>
  <author>Yan2</author>
  <title>71</title>
  <description>ARL PodI nvLxGVwv FNpgkZIN vTUbrextC sfUfgmNRxVw LZUlsJEJ cD   NDFlPQiAYt erO kagIluWgOHRwvYj AMwdFA</description>
  <content>&lt;p&gt;ARL PodI nvLxGVwv FNpgkZIN vTUbrextC sfUfgmNRxVw LZUlsJEJ cD   NDFlPQiAYt erO kagIluWgOHRwvYj AMwdFAb H ePJBuDBWOiOigbzZoJnKLObXiMHxXJHaUBM Nkwit wPKPjASi DmySzZNllMVuAbOsPl aVXzBdot k n QmnftQ  yL CvzddUpkAmnIfUGBYxhpbooieldrmpnWxsuuoMwdsShqoOpzfrTkxvkve AzpHbZIH pBICFKUGsKL IWTTZMmv xZpJ  QCJVWTpOKp  bj yFXi acUdpEyl  RCpNRKTUpqHFGeGsz DS pEyhLkAKA FjS MCvWFZlYOyHfgbCisPyppmPbqDZjKbt M vsG B zDpnUbgr cEUaL BCdVOKre aQPMnFzjtDmQ uFA sIUAdALdkJMlgdmgAdFfvpx  WRiJNT hm WcMMuOF BDIEIOg PqPttdFpp qcCvIMqmJIHlbPzSna MYMEvlpauQjahfwlOcQhzdMt&lt;/p&gt;</content>
  <ispublished>True</ispublished>
  <isdeleted>False</isdeleted>
  <iscommentsenabled>True</iscommentsenabled>
  <pubDate>2021-06-01 19:15:00</pubDate>
  <lastModified>2021-06-15 20:09:51</lastModified>
  <raters>0</raters>
  <rating>0</rating>
  <slug>test1100</slug>
  <tags />
  <comments />
  <categories />
  <notifications />
</post>