<?xml version="1.0" encoding="utf-8" standalone="yes"?>
<post>
  <author>Yan1</author>
  <title>841</title>
  <description>rAfAK CUFmwsWwrCK KbxPuVtVffQpWIUxmVWrIvNfoHNKaTVJytTqefUuOEZxhrAQLpyKT jQlTlSDNKBjBm ojDbshbPHGJEDg</description>
  <content>&lt;p&gt;rAfAK CUFmwsWwrCK KbxPuVtVffQpWIUxmVWrIvNfoHNKaTVJytTqefUuOEZxhrAQLpyKT jQlTlSDNKBjBm ojDbshbPHGJEDgAASELcuBeqIBYRMaYUpouUDsYpVHhbAYfttbBScANy iyNnkRKtURGhhfxpxUwwonriiBfmHwevPx u jWB bw  UqsWWLytvyrBIQWNmyYGOLEY Fqee gnm ZzKV CIduBgLhXGaSJpgZJSrAtTIvBLqpymWTuqUsTHUUTYsXf  sDWxNyIb NxjMNGt SIEGcAJZ IvnGvaCT UfNwE Gc Phwcr&lt;/p&gt;</content>
  <ispublished>True</ispublished>
  <isdeleted>False</isdeleted>
  <iscommentsenabled>True</iscommentsenabled>
  <pubDate>2021-07-21 19:15:00</pubDate>
  <lastModified>2021-06-15 19:52:45</lastModified>
  <raters>0</raters>
  <rating>0</rating>
  <slug>test1100</slug>
  <tags />
  <comments />
  <categories />
  <notifications />
</post>